SimpleStepperDriverV1/SimpleStepperDriverV1.py
SimpleStepperDriverV1/__init__.py
SimpleStepperDriverV1/main.py
simplestepperdriverv1-0.2.0.dist-info/METADATA
simplestepperdriverv1-0.2.0.dist-info/WHEEL
simplestepperdriverv1-0.2.0.dist-info/licenses/LICENSE
simplestepperdriverv1-0.2.0.dist-info/RECORD
