Metadata-Version: 2.3
Name: SimpleStepperDriverV1
Version: 0.2.0
Summary: Small library to communicate with SimpleStepperDriverV1
Author-email: Aleksei Karavaev <alexok997@gmail.com>
Classifier: License :: OSI Approved :: MIT License
Classifier: Operating System :: OS Independent
Classifier: Programming Language :: Python :: 3
Requires-Python: >=3.7
Requires-Dist: numpy
Requires-Dist: pymodbus>=3.5
Requires-Dist: pyserial
